framewise_secureline/__init__.py
framewise_secureline/client.py
framewise_secureline/exceptions.py
framewise_secureline/models.py
framewise_secureline-0.1.3.dist-info/METADATA
framewise_secureline-0.1.3.dist-info/WHEEL
framewise_secureline-0.1.3.dist-info/RECORD
